{
  "appPageId" : "a3e0f14f-7867-4f35-94b0-99ee54fe5116",
  "componentName" : "siteforce:sldsOneColLayout",
  "dataProviders" : [ ],
  "id" : "03e42aff-8774-4510-bc48-9fa1d0542745",
  "label" : "Messages",
  "regions" : [ {
    "components" : [ {
      "componentAttributes" : { },
      "componentName" : "forceChatter:messages",
      "id" : "f8728f99-a8c9-47f8-9fda-c221cd628d89",
      "renderPriority" : "NEUTRAL",
      "renditionMap" : { },
      "type" : "component"
    } ],
    "id" : "390886b6-ee7f-447a-8d49-f03193992c45",
    "regionName" : "content",
    "type" : "region"
  } ],
  "themeLayoutType" : "Inner",
  "type" : "view",
  "viewType" : "messages"
}